EasyNuitka/__init__.py
EasyNuitka/__main__.py
EasyNuitka/mainui.py
EasyNuitka/mainui.ui
EasyNuitka/resource.py
EasyNuitka/resource.qrc
EasyNuitka-1.1.2.3.dist-info/METADATA
EasyNuitka-1.1.2.3.dist-info/WHEEL
EasyNuitka-1.1.2.3.dist-info/top_level.txt
EasyNuitka-1.1.2.3.dist-info/RECORD
